inorgqm/__init__.py
inorgqm/multi_electron.py
inorgqm/utils.py
inorgqm/version.py
inorgqm-0.2.0.dist-info/METADATA
inorgqm-0.2.0.dist-info/WHEEL
inorgqm-0.2.0.dist-info/top_level.txt
inorgqm-0.2.0.dist-info/RECORD
