Metadata-Version: 2.1
Name: inorgqm
Version: 0.2.0
Summary: A package for working with phenomenological spin operators
Home-page: https://github.com/jonkragskow/inorgqm
Author: Jon Kragskow
Author-email: jonkragskow@gmail.com
Project-URL: Bug Tracker, https://github.com/jonkragskow/inorgqm/issues
Classifier: Programming Language :: Python :: 3
Classifier: License :: OSI Approved :: GNU General Public License v3 (GPLv3)
Classifier: Operating System :: OS Independent
Requires-Python: >=3.6
Requires-Dist: numpy
Requires-Dist: matplotlib
